{
    "list.source.grep.command": "rg",
    "list.source.grep.args": [
        "--smart-case"
    ],
    "suggest.triggerAfterInsertEnter": true,
    "languageserver": {
        "ccls": {
            "command": "ccls",
            "filetypes": [
                "c",
                "cpp",
                "objc",
                "objcpp"
            ],
            "rootPatterns": [
                ".ccls",
                "compile_commands.json",
                ".vim/",
                ".git/",
                ".hg/"
            ],
            "initializationOptions": {
                "cache": {
                    "directory": "/tmp/ccls"
                }
            }
        },
        "zls": {
            "command": "/Users/kubkon/dev/zls/zig-cache/bin/zls",
            "filetypes": ["zig"]
        }
    },
    "eslint.autoFixOnSave": true,
    "eslint.filetypes": [
      "javascript",
      "javascriptreact",
      "typescript",
      "typescriptreact"
    ],
    "prettier.disableSuccessMessage": true,
    "coc.preferences.formatOnSaveFiletypes": ["typescript", "typescriptreact"]
}
